queryparser/__init__.py
queryparser/adql/ADQLLexer.py
queryparser/adql/ADQLParser.py
queryparser/adql/ADQLParserListener.py
queryparser/adql/ADQLParserVisitor.py
queryparser/adql/__init__.py
queryparser/adql/adqlprocessor.py
queryparser/adql/adqltranslator.py
queryparser/common/__init__.py
queryparser/common/common.py
queryparser/exceptions/__init__.py
queryparser/mysql/MySQLLexer.py
queryparser/mysql/MySQLParser.py
queryparser/mysql/MySQLParserListener.py
queryparser/mysql/__init__.py
queryparser/mysql/mysqllisteners.py
queryparser/mysql/mysqlprocessor.py
queryparser/postgresql/PostgreSQLLexer.py
queryparser/postgresql/PostgreSQLParser.py
queryparser/postgresql/PostgreSQLParserListener.py
queryparser/postgresql/__init__.py
queryparser/postgresql/postgresqllisteners.py
queryparser/postgresql/postgresqlprocessor.py
queryparser_python3-0.7.4.dist-info/licenses/LICENSE
queryparser_python3-0.7.4.dist-info/METADATA
queryparser_python3-0.7.4.dist-info/WHEEL
queryparser_python3-0.7.4.dist-info/top_level.txt
queryparser_python3-0.7.4.dist-info/RECORD
