Metadata-Version: 2.4
Name: queryparser-python3
Version: 0.7.4
Summary: Package for parsing PostgreSQL/MySQL and translating ADQL to PostgreSQL/MySQL.
Author-email: Gal Matijevic <gmatijevic@aip.de>
Maintainer-email: Kirill Makan <kmakan@aip.de>, Simeon Reusch <sreusch@aip.de>
License: Apache-2.0
Project-URL: Repository, https://github.com/aipescience/queryparser.git
Project-URL: Issues, https://github.com/aipescience/queryparser/issues
Project-URL: Changelog, https://github.com/aipescience/queryparser/blob/master/CHANGELOG.md
Classifier: Development Status :: 5 - Production/Stable
Classifier: Intended Audience :: Developers
Classifier: Intended Audience :: Science/Research
Classifier: License :: OSI Approved :: Apache Software License
Classifier: Programming Language :: Python :: 3
Classifier: Programming Language :: Python :: 3 :: Only
Classifier: Programming Language :: Python :: 3.9
Classifier: Programming Language :: Python :: 3.10
Classifier: Programming Language :: Python :: 3.11
Requires-Python: >=3.9
License-File: LICENSE
Requires-Dist: antlr4-python3-runtime==4.13.1
Provides-Extra: test
Requires-Dist: pytest~=8.2.0; extra == "test"
Requires-Dist: PyYAML~=6.0; extra == "test"
Provides-Extra: dev
Requires-Dist: build; extra == "dev"
Requires-Dist: ruff; extra == "dev"
Requires-Dist: twine; extra == "dev"
Dynamic: license-file
